{
  "active_circuits": [
    "Solenoid",
    "P2_inner",
    "P2_outer",
    "P3",
    "P4",
    "P5",
    "P6"
  ],
  "filament_geometry": "R/Z filament lists and mean width/height (dR/dZ) from pf_active.zarr arrays (sol_*, p2_inner_*, p2_outer_*, p3_*, p4_*, p5_*, p6_*).",
  "files": [
    "active_coils.pickle",
    "limiter.pickle",
    "wall.pickle",
    "passive_coils.pickle"
  ],
  "honest_limits": [
    "Limiter/wall = FAIR-MAST wall.zarr EFIT limiter != surveyed CAD vessel",
    "No FreeGSNKE passives: pf_passive geometry exists but resistivity is unpublished",
    "P3/P6 have no measured FAIR-MAST voltage (evolutive uses I*R only)",
    "Active-coil resistivity = FreeGSNKE copper default 1.55e-08 (declared material constant)"
  ],
  "limiter": {
    "arrays": [
      "limiter_r",
      "limiter_z"
    ],
    "centroid_R_m": 1.0328177213668823,
    "centroid_Z_m": 0.010945945978164673,
    "n_points": 37,
    "not_cad_vessel": true,
    "provenance": "FAIR-MAST Level-2 wall.zarr limiter_r/z (EFIT limiter geometry). Not surveyed CAD vessel; not a flux-loop computational contour. Attr comment: Data sourced from EFIT file",
    "rule": "published_vertex_order_from_fairmast_wall",
    "source": "wall.zarr",
    "zarr_comment": "Data sourced from EFIT file"
  },
  "machine": "classic_MAST",
  "note": "Replaces FreeGSNKE public MAST-U-like structural pickles for FAIR-MAST classic MAST shots. Archived prior pickles under archive_mastu_like/ when present.",
  "passives": {
    "geometry_components": [
      "botcol",
      "coil_cases",
      "endcrown_l",
      "endcrown_u",
      "incon",
      "lhorw",
      "mid",
      "p2larm",
      "p2ldivpl",
      "p2uarm",
      "p2udivpl",
      "ring",
      "rodgr",
      "topcol",
      "uhorw",
      "vertw"
    ],
    "passives_written": [],
    "pf_passive_zarr_present": true,
    "reason": "FAIR-MAST Level-2 pf_passive publishes parallelogram geometry (r/z/width/height/shapeAngle1/shapeAngle2) but no resistivity; FreeGSNKE passive pickles require resistivity. Do not invent resistivity \u2014 passive_coils.pickle stays empty.",
    "resistivity_keys_found": []
  },
  "polarity": "+1 for all filaments (declared)",
  "resistivity_citation": "FreeGSNKE default copper resistivity used in public machine_configs (value 1.55e-08); material constant \u2014 not invented coil geometry. FAIR-MAST Level-2 pf_active does not publish coil resistivity.",
  "resistivity_ohm_m": 1.55e-08,
  "shot": 30201,
  "shot_cache": "data_cache\\shot_30201",
  "source": "FAIR-MAST Level-2 Zarr (classic MAST \u2014 not MAST-U)",
  "source_fingerprints": {
    "pf_active": {
      "keys": [
        "p2_inner_lower_height",
        "p2_inner_lower_r",
        "p2_inner_lower_width",
        "p2_inner_lower_z",
        "p2_inner_upper_height",
        "p2_inner_upper_r",
        "p2_inner_upper_width",
        "p2_inner_upper_z",
        "p2_outer_lower_height",
        "p2_outer_lower_r",
        "p2_outer_lower_width",
        "p2_outer_lower_z",
        "p2_outer_upper_height",
        "p2_outer_upper_r",
        "p2_outer_upper_width",
        "p2_outer_upper_z",
        "p3_lower_height",
        "p3_lower_r",
        "p3_lower_width",
        "p3_lower_z",
        "p3_upper_height",
        "p3_upper_r",
        "p3_upper_width",
        "p3_upper_z",
        "p4_lower_height",
        "p4_lower_r",
        "p4_lower_width",
        "p4_lower_z",
        "p4_upper_height",
        "p4_upper_r",
        "p4_upper_width",
        "p4_upper_z",
        "p5_lower_height",
        "p5_lower_r",
        "p5_lower_width",
        "p5_lower_z",
        "p5_upper_height",
        "p5_upper_r",
        "p5_upper_width",
        "p5_upper_z",
        "p6_lower_height",
        "p6_lower_r",
        "p6_lower_width",
        "p6_lower_z",
        "p6_upper_height",
        "p6_upper_r",
        "p6_upper_width",
        "p6_upper_z",
        "sol_height",
        "sol_r",
        "sol_width",
        "sol_z"
      ],
      "path": "data_cache\\shot_30201\\pf_active.zarr",
      "sha256": "7f5c6f6373a5c01d9f0dd8f516d5923e7305afaeacdfbe53be6959741505c8eb"
    },
    "wall": {
      "keys": [
        "limiter_r",
        "limiter_z"
      ],
      "path": "data_cache\\shot_30201\\wall.zarr",
      "sha256": "b8ce3723373f2111d48400765915e81f228a732fb14847d1d60c1baa2effb296"
    }
  },
  "source_repo": "https://github.com/ukaea/fair-mast",
  "wall": "set equal to wall.zarr limiter contour (EFIT limiter geometry; not CAD vessel)"
}
